{
  "roles-represented" : [ "medical-assistant" ], // bound to extend assistant
  "object" : {
    "ch.elexis.core.model.ILaboratory" : "cruvd",
    "ch.elexis.core.model.IPerson" : "cruvd",
    "ch.elexis.core.model.IPatient" : "cruvd",
    "ch.elexis.core.model.ILabItem" : "cruvd",
    "ch.elexis.core.model.ILabResult" : "cruvd",
    "ch.elexis.core.model.ILabMapping" : "cruvd",
    "ch.elexis.core.model.ILabOrder" : "cruvd",
    "ch.elexis.core.model.IEncounter" : "crv:aobo",
    "ch.elexis.core.model.IBillable" : "cruvd",
    "ch.elexis.core.model.IBilled" : "cruvd:aobo",
    "ch.elexis.core.model.IPrescription": "rv:aobo",
    "ch.elexis.core.model.IInvoice": "rv:aobo"
  }
}